{"stop_id":"70224","stop_name":"Summit Avenue - Inbound","mode":[{"route_type":"0","mode_name":"Subway","route":[{"route_id":"Green-C","route_name":"Green Line C","direction":[{"direction_id":"1","direction_name":"Eastbound","trip":[{"trip_id":"942_1","trip_name":"C train from Cleveland Circle to North Station","trip_headsign":"North Station","pre_dt":"1464571668","pre_away":"213","vehicle":{"vehicle_id":"3810","vehicle_lat":"42.33891","vehicle_lon":"-71.1368","vehicle_bearing":"71","vehicle_timestamp":"1464571440"}}]}]}]}],"alert_headers":[]}
